LICENSE
events/__init__.py
events/admin.py
events/apps.py
events/cms_apps.py
events/migrations/0001_initial.py
events/migrations/0002_add_climatecare_fields.py
events/migrations/0003_make_fields_optional.py
events/migrations/0004_auto_20220509_0816.py
events/migrations/0005_event_hero_image.py
events/migrations/__init__.py
events/models.py
events/sitemaps.py
events/templates/base.html
events/templates/events/detail.html
events/templates/events/index.html
events/tests/__init__.py
events/tests/conftest.py
events/tests/test_cms_apps.py
events/tests/test_models.py
events/tests/test_views.py
events/tests/urls.py
events/urls.py
events/views.py
giant_events-0.3.0.2.dist-info/LICENSE
giant_events-0.3.0.2.dist-info/METADATA
giant_events-0.3.0.2.dist-info/WHEEL
giant_events-0.3.0.2.dist-info/RECORD
