Metadata-Version: 2.1
Name: giant-events
Version: 0.3.0.2
Summary: A small reusable package that adds an Events app to a project
Home-page: https://github.com/giantmade/giant-events
License: MIT
Keywords: events,app
Author: Will-Hoey
Author-email: will.hoey@giantmade.com
Requires-Python: >=3.6.2,<4.0.0
Classifier: Environment :: Console
Classifier: License :: OSI Approved :: MIT License
Classifier: Operating System :: OS Independent
Classifier: Programming Language :: Python :: 3
Classifier: Programming Language :: Python :: 3.7
Classifier: Programming Language :: Python :: 3.8
Classifier: Programming Language :: Python :: 3.9
Classifier: Programming Language :: Python :: 3.10
Classifier: Programming Language :: Python :: 3.11
Classifier: Topic :: Software Development :: Documentation
Classifier: Topic :: Software Development :: Libraries :: Python Modules
Requires-Dist: django-filer
Requires-Dist: giant-mixins
Project-URL: Repository, https://github.com/giantmade/giant-events
